{
  "isSuccess": true,
  "data": [
    {
      "pageNumber": 175,
      "sectionNumber": 2,
      "hasTextContent": true,
      "hasImageContent": true,
      "paragList": [
        {
          "paragraphId": 714167032,
          "paragNumber": 1,
          "tocNumber": 0,
          "text": "<p id=\"2931\"><format class=\"hadith\" who=\"6\" Id=\"269\" RevayatIndex=\"269\">فقال: «أوّلها الجذام، و الثاني الريح الخبيثة التي تنزل في الوجه و الرأس، و الثالثة من نزول الماء في العين، و الرابعة سدّة الخياشيم، و الخامسة خروج الشعر <page number=\"175\"/> في العين، فإن أحببت أن يقلّ عطاسك فاسعط بدهن المرزنجوش».</format></p>"
        },
        {
          "paragraphId": 714167033,
          "paragNumber": 2,
          "tocNumber": 0,
          "text": "<p id=\"2932\"><format class=\"hadith\" who=\"6\" Id=\"269\" RevayatIndex=\"269\">قلت: بمقدار كم‌؟</format></p>"
        },
        {
          "paragraphId": 714167034,
          "paragNumber": 3,
          "tocNumber": 0,
          "text": "<p id=\"2933\"><format class=\"hadith\" who=\"6\" Id=\"269\" RevayatIndex=\"269\">قال: «بمقدار دانق».</format></p>"
        },
        {
          "paragraphId": 714167035,
          "paragNumber": 4,
          "tocNumber": 0,
          "text": "<p id=\"2934\"><format class=\"hadith\" who=\"6\" Id=\"269\" RevayatIndex=\"269\">قال: ففعلت ذلك<lfootnote noteId=\"1049\">1</lfootnote> خمسة أيّام فذهب عنّي<lfootnote noteId=\"1050\">2</lfootnote>.</format></p>"
        },
        {
          "paragraphId": 714167036,
          "paragNumber": 5,
          "tocNumber": 0,
          "text": "<p id=\"2935\">[272] </p>"
        },
        {
          "paragraphId": 714167037,
          "paragNumber": 6,
          "tocNumber": 0,
          "text": "<p id=\"2936\"><format class=\"hadith\" who=\"6\" Id=\"270\" RevayatIndex=\"270\"><format class=\"sanadHadith\">و روي عنه عليه السّلام أنّه قال: </format><format class=\"Y\"><format class=\"maasoom\" maasoomNo=\"6\"/></format>«من عطس في مرضه كان أمانا له من أن يموت في تلك العلّة»<lfootnote noteId=\"1051\">3</lfootnote>.</format></p>"
        },
        {
          "paragraphId": 714167038,
          "paragNumber": 7,
          "tocNumber": 0,
          "text": "<p id=\"2937\"><page number=\"176\"/>[273] </p>"
        }
      ],
      "taliqehList": null,
      "footnoteList": [
        {
          "footnoteId": 714169093,
          "text": "<footnote id=\"1049\"><page number=\"175\"/><mnote>(1)</mnote> قوله: «قال» و «ذلك» أثبتناه من مكارم الأخلاق. </footnote>"
        },
        {
          "footnoteId": 714169094,
          "text": "<footnote id=\"1050\"><mnote>(2)</mnote> روى الطبرسي نحوه في مكارم الأخلاق: 14/355، في العطاس، فقال: روى أبو بصير، عن أبي عبد الله عليه السّلام قال: «كثرة العطاس يأمن صاحبه من خمسة أشياء أوّلها الجذام، و الثاني: الريح الخبيثة التي تنزل في الرأس و الوجه، و الثالث: يأمن من نزول الماء في العين، و الرابع: يأمن من سدّة الخياشيم، و الخامس: يأمن من خروج الشعر في العين». قال عليه السّلام: «و إن أحببت أن تقلّ عطاسك فاستعط بدهن المرزنجوش»، قلت:<br/>مقدار كم‌؟ قال: «مقدار دانق»، قال: ففعلت ذلك خمسة أيّام فذهب عنّي. فكأنّ الطبرسي رحمه الله دمج بين هذه الرواية و سابقتها فجعلهما واحدة. </footnote>"
        },
        {
          "footnoteId": 714169095,
          "text": "<footnote id=\"1051\"><mnote>(3)</mnote> رواه الطبرسي في مكارم الأخلاق: 15/356، باب العطاس، بعد الحديث المتقدّم عن أبي عبد الله عليه السّلام.<br/>و في رواية: «صاحب العطسة يأمن الموت سبعة أيّام». و في رواية عن صاحب الزمان عليه السّلام: «صاحب العطسة يأمن الموت ثلاثة أيّام». انظر: الكافي 23/657:2، كمال الدين: 5/430 و 11/441، الهداية الكبرى للخصيبي: 358، إثبات الوصيّة:<br/>261، الغيبة للطوسي: 20/232، إعلام الورى 217:2، مكارم الأخلاق: 354، الثاقب في المناقب: 180/203، الخرائج و الجرائح 11/465:1 و ج 7/693:2، الدعوات: 544/198، كشف الغمة 500:2، منتخب الأنوار المضيئة: 160، <page number=\"176\"/>الصراط المستقيم 235:2. </footnote>"
        }
      ],
      "pageValue": "175",
      "isFreeStudy": true,
      "requestedContentType": "text",
      "providedContentType": "text",
      "isEmpty": false,
      "html": "<div class=\"CODE\">\n  <p id=\"p2931\" paragraph-id=\"2931\" class=\" G\">\n    <span class=\"hadith\">\n      <span class=\"GPA0 bookPage PageNo175\">175</span> في العين، فإن أحببت أن يقلّ عطاسك فاسعط بدهن المرزنجوش».</span>\n  </p>\n  <p id=\"p2932\" paragraph-id=\"2932\" class=\" G\">\n    <span class=\"hadith\">قلت: بمقدار كم‌؟</span>\n  </p>\n  <p id=\"p2933\" paragraph-id=\"2933\" class=\" G\">\n    <span class=\"hadith\">قال: «بمقدار دانق».</span>\n  </p>\n  <p id=\"p2934\" paragraph-id=\"2934\" class=\" G\">\n    <span class=\"hadith\">قال: ففعلت ذلك<span><sup><a class=\"NewFn\" href=\"#footnote1049\" title=\"(1)  قوله: «قال» و «ذلك» أثبتناه من مكارم الأخلاق. \">1</a></sup></span> خمسة أيّام فذهب عنّي<span><sup><a class=\"NewFn\" href=\"#footnote1050\" title=\"(2)  روى الطبرسي نحوه في مكارم الأخلاق: 14/355، في العطاس، فقال: روى أبو بصير، عن أبي عبد الله عليه السّلام قال: «كثرة العطاس يأمن صاحبه من خمسة أشياء أوّلها الجذام، و الثاني: الريح الخبيثة التي تنزل في الرأس و الوجه، و الثالث: يأمن من نزول الماء في العين، و الرابع: يأمن من سدّة الخياشيم، و الخامس: يأمن من خروج الشعر في العين». قال عليه السّلام: «و إن أحببت أن تقلّ عطاسك فاستعط بدهن المرزنجوش»، قلت:مقدار كم‌؟ قال: «مقدار دانق»، قال: ففعلت ذلك خمسة أيّام فذهب عنّي. فكأنّ الطبرسي رحمه الله دمج بين هذه الرواية و سابقتها فجعلهما واحدة. \">2</a></sup></span>.</span>\n  </p>\n  <p id=\"p2935\" paragraph-id=\"2935\" class=\" G\">[272] </p>\n  <p id=\"p2936\" paragraph-id=\"2936\" class=\" G\">\n    <span class=\"hadith\">\n      <span class=\"sanadHadith\">و روي عنه عليه السّلام أنّه قال: </span>\n      <span class=\"Y\">\n        <span class=\"maasoom\"></span>\n      </span>«من عطس في مرضه كان أمانا له من أن يموت في تلك العلّة»<span><sup><a class=\"NewFn\" href=\"#footnote1051\" title=\"(3)  رواه الطبرسي في مكارم الأخلاق: 15/356، باب العطاس، بعد الحديث المتقدّم عن أبي عبد الله عليه السّلام.و في رواية: «صاحب العطسة يأمن الموت سبعة أيّام». و في رواية عن صاحب الزمان عليه السّلام: «صاحب العطسة يأمن الموت ثلاثة أيّام». انظر: الكافي 23/657:2، كمال الدين: 5/430 و 11/441، الهداية الكبرى للخصيبي: 358، إثبات الوصيّة:261، الغيبة للطوسي: 20/232، إعلام الورى 217:2، مكارم الأخلاق: 354، الثاقب في المناقب: 180/203، الخرائج و الجرائح 11/465:1 و ج 7/693:2، الدعوات: 544/198، كشف الغمة 500:2، منتخب الأنوار المضيئة: 160، \">3</a></sup></span>.</span>\n  </p>\n  <p id=\"p2937\" paragraph-id=\"2937\" class=\" G\" />\n  <hr class=\"footnoteLine\" />\n  <span>\n    <div class=\"footnote OriginalDigit\" id=\"footnote1049\" footnote-id=\"1049\">(1) <page number=\"175\" /> قوله: «قال» و «ذلك» أثبتناه من مكارم الأخلاق. </div>\n    <div class=\"footnote OriginalDigit\" id=\"footnote1050\" footnote-id=\"1050\">(2)  روى الطبرسي نحوه في مكارم الأخلاق: 14/355، في العطاس، فقال: روى أبو بصير، عن أبي عبد الله عليه السّلام قال: «كثرة العطاس يأمن صاحبه من خمسة أشياء أوّلها الجذام، و الثاني: الريح الخبيثة التي تنزل في الرأس و الوجه، و الثالث: يأمن من نزول الماء في العين، و الرابع: يأمن من سدّة الخياشيم، و الخامس: يأمن من خروج الشعر في العين». قال عليه السّلام: «و إن أحببت أن تقلّ عطاسك فاستعط بدهن المرزنجوش»، قلت:<br />مقدار كم‌؟ قال: «مقدار دانق»، قال: ففعلت ذلك خمسة أيّام فذهب عنّي. فكأنّ الطبرسي رحمه الله دمج بين هذه الرواية و سابقتها فجعلهما واحدة. </div>\n    <div class=\"footnote OriginalDigit\" id=\"footnote1051\" footnote-id=\"1051\">(3)  رواه الطبرسي في مكارم الأخلاق: 15/356، باب العطاس، بعد الحديث المتقدّم عن أبي عبد الله عليه السّلام.<br />و في رواية: «صاحب العطسة يأمن الموت سبعة أيّام». و في رواية عن صاحب الزمان عليه السّلام: «صاحب العطسة يأمن الموت ثلاثة أيّام». انظر: الكافي 23/657:2، كمال الدين: 5/430 و 11/441، الهداية الكبرى للخصيبي: 358، إثبات الوصيّة:<br />261، الغيبة للطوسي: 20/232، إعلام الورى 217:2، مكارم الأخلاق: 354، الثاقب في المناقب: 180/203، الخرائج و الجرائح 11/465:1 و ج 7/693:2، الدعوات: 544/198، كشف الغمة 500:2، منتخب الأنوار المضيئة: 160، </div>\n  </span>\n</div>",
      "bookPageVisitLogId": "79762CAD-AD42-4136-AD65-6AF7A5CB7F86",
      "validation": {
        "code": 1,
        "type": "successful",
        "message": "محتوا در دسترس می باشد -  کتاب یا محدوده رایگان"
      }
    }
  ],
  "totalCount": 1,
  "statusCode": 200,
  "message": "OK",
  "exception": null,
  "validationMessages": null
}