{
  "isSuccess": true,
  "data": [
    {
      "pageNumber": 287,
      "sectionNumber": 2,
      "hasTextContent": true,
      "hasImageContent": true,
      "paragList": [
        {
          "paragraphId": 714167764,
          "paragNumber": 1,
          "tocNumber": 0,
          "text": "<p id=\"3510\">[468] روى السيّاري، يرفعه قال: يؤخذ لصاحب حصور<lfootnote noteId=\"1573\">4</lfootnote> البول رطلين <page number=\"287\"/> من ماء الفجلّ و مثله مطبوخ و هو العجيم الجيّد و رطلين ذرق الحمام، يطبخ كلّه و يسقى منه كلّ يوم رطلا<lfootnote noteId=\"1574\">1</lfootnote><lfootnote noteId=\"1575\"> 2</lfootnote>.</p>"
        },
        {
          "paragraphId": 714167765,
          "paragNumber": 2,
          "tocNumber": 0,
          "text": "<p id=\"3511\">[469] </p>"
        },
        {
          "paragraphId": 714167766,
          "paragNumber": 3,
          "tocNumber": 0,
          "text": "<p id=\"3512\"><format class=\"hadith\" who=\"10\" Id=\"461\" RevayatIndex=\"461\"><format class=\"sanadHadith\">حدّثنا ابن همّام، قال حدّثنا الحميري، و روى محمّد بن الحسن الصفّار جميعا، عن حمران قال:</format> كتبت إلى <format class=\"Y\"><format class=\"maasoom\" maasoomNo=\"10\">أبي الحسن الثالث عليه السّلام</format></format>: جعلت فداك قبلي<lfootnote noteId=\"1576\">3</lfootnote> رجل من مواليك، به حصر البول، و هو يسألك الدعاء أن يلبسه الله العافية من علّته و اسمه: نفيس الخادم.</format></p>"
        },
        {
          "paragraphId": 714167767,
          "paragNumber": 4,
          "tocNumber": 0,
          "text": "<p id=\"3513\"><format class=\"hadith\" who=\"10\" Id=\"461\" RevayatIndex=\"461\">فأجاب: «كشف الله ضرّك و دفع عنك<lfootnote noteId=\"1577\">4</lfootnote> مكاره الدنيا و الآخرة، و ألحّ عليه بالقرآن، فإنّه يشفى إن شاء الله تعالى»<lfootnote noteId=\"1578\">5</lfootnote>.</format></p>"
        },
        {
          "paragraphId": 714167768,
          "paragNumber": 5,
          "tocNumber": 0,
          "text": "<p id=\"3514\"><heading level=\"2\">[باب] علاج من يبول في الفراش </heading></p>"
        },
        {
          "paragraphId": 714167769,
          "paragNumber": 6,
          "tocNumber": 0,
          "text": "<p id=\"3515\">[470] </p>"
        },
        {
          "paragraphId": 714167770,
          "paragNumber": 7,
          "tocNumber": 0,
          "text": "<p id=\"3516\"><format class=\"hadith\" who=\"16\" Id=\"462\" RevayatIndex=\"462\"><format class=\"sanadHadith\">روي عنهم عليهم السّلام ممّا وجدته في كتاب ابن البندار و حذفت إسناده:</format></format></p>"
        },
        {
          "paragraphId": 714167771,
          "paragNumber": 8,
          "tocNumber": 0,
          "text": "<p id=\"3517\"><format class=\"hadith\" who=\"16\" Id=\"462\" RevayatIndex=\"462\"><format class=\"sanadHadith\"/>«يؤخذ جزء<lfootnote noteId=\"1579\">6</lfootnote> من سعد و جزء من زعفران، و يدقّ كلّ واحد منهما على حدة و ينخل السعد بحريرة صفيقة، و يخلطان جميعا بعسل منزوع الرغوة، ثمّ تبندق، <page number=\"288\"/> و يكتب في جام حديد<lfootnote noteId=\"1580\">1</lfootnote> بزعفران: <format class=\"ayah\" surah=\"1\" ayah=\"1\" toAyah=\"\">بِسْمِ اَللّٰهِ اَلرَّحْمٰنِ اَلرَّحِيمِ <format class=\"ayahWord\" fromWord=\"1\" toWord=\"4\"/><format class=\"ayahAddress\" surah=\"1\" ayah=\"1\" toAyah=\"\"/></format><format class=\"ayah\" surah=\"35\" ayah=\"41\" toAyah=\"\">إِنَّ اَللّٰهَ يُمْسِكُ اَلسَّمٰاوٰاتِ وَ اَلْأَرْضَ أَنْ تَزُولاٰ وَ لَئِنْ زٰالَتٰا إِنْ أَمْسَكَهُمٰا مِنْ أَحَدٍ مِنْ بَعْدِهِ إِنَّهُ كٰانَ حَلِيماً غَفُوراً<format class=\"ayahWord\" fromWord=\"1\" toWord=\"21\"/><format class=\"ayahAddress\" surah=\"35\" ayah=\"41\" toAyah=\"\"/></format><lfootnote noteId=\"1581\">2</lfootnote> تملأ الجام من هذه الآية مرّة بعد مرّة، ثمّ تغسلها بماء بارد و تصبّه في قنّينة نظيفة، و يؤخذ ورق<lfootnote noteId=\"1582\">3</lfootnote> فيكتب فيه بمداد هذه الآية و فاتحة<lfootnote noteId=\"1583\">4</lfootnote>الكتاب و <format class=\"ayah\" surah=\"112\" ayah=\"1\" toAyah=\"\">قُلْ هُوَ اَللّٰهُ أَحَدٌ<format class=\"ayahWord\" fromWord=\"1\" toWord=\"4\"/><format class=\"ayahAddress\" surah=\"112\" ayah=\"1\" toAyah=\"\"/></format> ثلاث مرّات و المعوّذتين و آية الكرسي كما أنزلت و آخر الحشر و آخر بني إسرائيل، ثمّ يكتب <format class=\"ayah\" surah=\"1\" ayah=\"1\" toAyah=\"\">بِسْمِ اَللّٰهِ اَلرَّحْمٰنِ اَلرَّحِيمِ <format class=\"ayahWord\" fromWord=\"1\" toWord=\"4\"/><format class=\"ayahAddress\" surah=\"1\" ayah=\"1\" toAyah=\"\"/></format><format class=\"ayah\" surah=\"35\" ayah=\"41\" toAyah=\"\">إِنَّ اَللّٰهَ يُمْسِكُ اَلسَّمٰاوٰاتِ وَ اَلْأَرْضَ‌...<format class=\"ayahWord\" fromWord=\"1\" toWord=\"6\"/><format class=\"ayahAddress\" surah=\"35\" ayah=\"41\" toAyah=\"\"/></format> إلى <format class=\"ayah\" surah=\"35\" ayah=\"41\" toAyah=\"\">حَلِيماً غَفُوراً<format class=\"ayahWord\" fromWord=\"20\" toWord=\"21\"/><format class=\"ayahAddress\" surah=\"35\" ayah=\"41\" toAyah=\"\"/></format>، و يكتب: يا من هو هكذا و لا هكذا غيره، أمسك عن فلان بن فلانة - و إن كانت ابنة: عن فلانة - ما يجد من غلبة البول. و يعلّق التعويذ على ركبتها إن كانت انثى<lfootnote noteId=\"1584\">5</lfootnote> و إن كان غلاما على موضع العانة و على إحليله، و تؤخذ بندقة من تلك البنادق و يسقيه إيّاها حين يأخذ مضجعه بشيء من ذلك الماء المعوّذ، و ليقلّ من شرب الماء، فإذا ذهب ما يجد من غلبة<lfootnote noteId=\"1585\">6</lfootnote> البول فليحلّ‌<lfootnote noteId=\"1586\">7</lfootnote> التعويذ عنه و إلّا اعتراه الحصر»<lfootnote noteId=\"1587\">8</lfootnote>.</format></p>"
        }
      ],
      "taliqehList": null,
      "footnoteList": [
        {
          "footnoteId": 714169529,
          "text": "<footnote id=\"1574\"><page number=\"287\"/><mnote>(1)</mnote> في النسخة زيادة: «منه». </footnote>"
        },
        {
          "footnoteId": 714169530,
          "text": "<footnote id=\"1575\"><mnote>(2)</mnote> لم نعثر عليه في المصادر المتوفّرة لدينا، و وجد نحو هذا الدواء في بعض الكتب الطبيّة القديمة لعلاج الحصاة و عسر البول، فلاحظ: الذخيرة: 181، كامل الصناعة الطبّيّة 142:4. </footnote>"
        },
        {
          "footnoteId": 714169531,
          "text": "<footnote id=\"1576\"><mnote>(3)</mnote> في هامش النسخة: «قبل» و في مكارم الأخلاق: «قبيلي». </footnote>"
        },
        {
          "footnoteId": 714169532,
          "text": "<footnote id=\"1577\"><mnote>(4)</mnote> كذا في النسخة و في مكارم الأخلاق، و الصواب: «كشف الله ضرّه و دفع عنه». </footnote>"
        },
        {
          "footnoteId": 714169533,
          "text": "<footnote id=\"1578\"><mnote>(5)</mnote> رواه الطبرسي في مكارم الأخلاق: 2/379، لاحتباس البول، عن حمران قال: كتبت إلى أبي الحسن الثالث عليه السّلام. </footnote>"
        },
        {
          "footnoteId": 714169534,
          "text": "<footnote id=\"1579\"><mnote>(6)</mnote> في مكارم الأخلاق: «يؤخذ جزءان».</footnote>"
        }
      ],
      "pageValue": "287",
      "isFreeStudy": true,
      "requestedContentType": "text",
      "providedContentType": "text",
      "isEmpty": false,
      "html": "<div class=\"CODE\">\n  <p id=\"p3510\" paragraph-id=\"3510\" class=\" G\">\n    <span class=\"GPA0 bookPage PageNo287\">287</span> من ماء الفجلّ و مثله مطبوخ و هو العجيم الجيّد و رطلين ذرق الحمام، يطبخ كلّه و يسقى منه كلّ يوم رطلا<span><sup><a class=\"NewFn\" href=\"#footnote1574\" title=\"(1)  في النسخة زيادة: «منه». \">1</a></sup></span><span><sup><a class=\"NewFn\" href=\"#footnote1575\" title=\"(2)  لم نعثر عليه في المصادر المتوفّرة لدينا، و وجد نحو هذا الدواء في بعض الكتب الطبيّة القديمة لعلاج الحصاة و عسر البول، فلاحظ: الذخيرة: 181، كامل الصناعة الطبّيّة 142:4. \"> 2</a></sup></span>.</p>\n  <p id=\"p3511\" paragraph-id=\"3511\" class=\" G\">[469] </p>\n  <p id=\"p3512\" paragraph-id=\"3512\" class=\" G\">\n    <span class=\"hadith\">\n      <span class=\"sanadHadith\">حدّثنا ابن همّام، قال حدّثنا الحميري، و روى محمّد بن الحسن الصفّار جميعا، عن حمران قال:</span> كتبت إلى <span class=\"Y\"><span class=\"maasoom\">أبي الحسن الثالث عليه السّلام</span></span>: جعلت فداك قبلي<span><sup><a class=\"NewFn\" href=\"#footnote1576\" title=\"(3)  في هامش النسخة: «قبل» و في مكارم الأخلاق: «قبيلي». \">3</a></sup></span> رجل من مواليك، به حصر البول، و هو يسألك الدعاء أن يلبسه الله العافية من علّته و اسمه: نفيس الخادم.</span>\n  </p>\n  <p id=\"p3513\" paragraph-id=\"3513\" class=\" G\">\n    <span class=\"hadith\">فأجاب: «كشف الله ضرّك و دفع عنك<span><sup><a class=\"NewFn\" href=\"#footnote1577\" title=\"(4)  كذا في النسخة و في مكارم الأخلاق، و الصواب: «كشف الله ضرّه و دفع عنه». \">4</a></sup></span> مكاره الدنيا و الآخرة، و ألحّ عليه بالقرآن، فإنّه يشفى إن شاء الله تعالى»<span><sup><a class=\"NewFn\" href=\"#footnote1578\" title=\"(5)  رواه الطبرسي في مكارم الأخلاق: 2/379، لاحتباس البول، عن حمران قال: كتبت إلى أبي الحسن الثالث عليه السّلام. \">5</a></sup></span>.</span>\n  </p>\n  <p id=\"p3514\" paragraph-id=\"3514\" class=\" G\">\n    <strong style=\"0\" class=\"h-2 02\">[باب] علاج من يبول في الفراش </strong>\n  </p>\n  <p id=\"p3515\" paragraph-id=\"3515\" class=\" G\">[470] </p>\n  <p id=\"p3516\" paragraph-id=\"3516\" class=\" G\">\n    <span class=\"hadith\">\n      <span class=\"sanadHadith\">روي عنهم عليهم السّلام ممّا وجدته في كتاب ابن البندار و حذفت إسناده:</span>\n    </span>\n  </p>\n  <p id=\"p3517\" paragraph-id=\"3517\" class=\" G\">\n    <span class=\"hadith\">\n      <span class=\"sanadHadith\"></span>«يؤخذ جزء<span><sup><a class=\"NewFn\" href=\"#footnote1579\" title=\"(6)  في مكارم الأخلاق: «يؤخذ جزءان».\">6</a></sup></span> من سعد و جزء من زعفران، و يدقّ كلّ واحد منهما على حدة و ينخل السعد بحريرة صفيقة، و يخلطان جميعا بعسل منزوع الرغوة، ثمّ تبندق، </span>\n  </p>\n  <hr class=\"footnoteLine\" />\n  <span>\n    <div class=\"footnote OriginalDigit\" id=\"footnote1574\" footnote-id=\"1574\">(1) <page number=\"287\" /> في النسخة زيادة: «منه». </div>\n    <div class=\"footnote OriginalDigit\" id=\"footnote1575\" footnote-id=\"1575\">(2)  لم نعثر عليه في المصادر المتوفّرة لدينا، و وجد نحو هذا الدواء في بعض الكتب الطبيّة القديمة لعلاج الحصاة و عسر البول، فلاحظ: الذخيرة: 181، كامل الصناعة الطبّيّة 142:4. </div>\n    <div class=\"footnote OriginalDigit\" id=\"footnote1576\" footnote-id=\"1576\">(3)  في هامش النسخة: «قبل» و في مكارم الأخلاق: «قبيلي». </div>\n    <div class=\"footnote OriginalDigit\" id=\"footnote1577\" footnote-id=\"1577\">(4)  كذا في النسخة و في مكارم الأخلاق، و الصواب: «كشف الله ضرّه و دفع عنه». </div>\n    <div class=\"footnote OriginalDigit\" id=\"footnote1578\" footnote-id=\"1578\">(5)  رواه الطبرسي في مكارم الأخلاق: 2/379، لاحتباس البول، عن حمران قال: كتبت إلى أبي الحسن الثالث عليه السّلام. </div>\n    <div class=\"footnote OriginalDigit\" id=\"footnote1579\" footnote-id=\"1579\">(6)  في مكارم الأخلاق: «يؤخذ جزءان».</div>\n  </span>\n</div>",
      "bookPageVisitLogId": "DF023F62-FA25-46A0-9826-7F2491B205A1",
      "validation": {
        "code": 1,
        "type": "successful",
        "message": "محتوا در دسترس می باشد -  کتاب یا محدوده رایگان"
      }
    }
  ],
  "totalCount": 1,
  "statusCode": 200,
  "message": "OK",
  "exception": null,
  "validationMessages": null
}