{
  "isSuccess": true,
  "data": [
    {
      "pageNumber": 143,
      "sectionNumber": 2,
      "hasTextContent": true,
      "hasImageContent": true,
      "paragList": [
        {
          "paragraphId": 714167159,
          "paragNumber": 1,
          "tocNumber": 0,
          "text": "<p id=\"2756\"><page number=\"143\"/>[215] </p>"
        },
        {
          "paragraphId": 714167160,
          "paragNumber": 2,
          "tocNumber": 0,
          "text": "<p id=\"2757\"><format class=\"hadith\" who=\"6\" Id=\"213\" RevayatIndex=\"213\"><format class=\"sanadHadith\">و روي عن <format class=\"Y\"><format class=\"maasoom\" maasoomNo=\"6\">أبي عبد الله عليه السّلام</format></format> أنّه قال: </format>«غسل الرأس بالخطمي ينفي الفقر و يزيد في الرزق»<lfootnote noteId=\"902\">1</lfootnote>.</format></p>"
        },
        {
          "paragraphId": 714167161,
          "paragNumber": 3,
          "tocNumber": 0,
          "text": "<p id=\"2758\">[216] </p>"
        },
        {
          "paragraphId": 714167162,
          "paragNumber": 4,
          "tocNumber": 0,
          "text": "<p id=\"2759\"><format class=\"hadith\" who=\"14,6\" Id=\"214\" RevayatIndex=\"214\"><format class=\"sanadHadith\">و قال: </format><format class=\"Y\"><format class=\"maasoom\" maasoomNo=\"6\"/></format>«إنّ <format class=\"Y\"><format class=\"maasoom\" maasoomNo=\"14\">رسول الله صلّى الله عليه و آله</format></format> اغتمّ ذات يوم فأمره جبريل عليه السّلام أن يغسل رأسه بالسدر»<lfootnote noteId=\"903\">2</lfootnote>.</format></p>"
        },
        {
          "paragraphId": 714167163,
          "paragNumber": 5,
          "tocNumber": 0,
          "text": "<p id=\"2760\"><page number=\"144\"/>[217] </p>"
        }
      ],
      "taliqehList": null,
      "footnoteList": [
        {
          "footnoteId": 714168857,
          "text": "<footnote id=\"902\"><page number=\"143\"/><mnote>(1)</mnote> رواه الصدوق في من لا يحضره الفقيه 291/124:1، عن الصادق عليه السّلام - و عنه في مكارم الأخلاق: 2/60، الفصل الخامس في غسل الرأس بالخطمي و السدر - و في ثواب الأعمال: 2/19، باب ثواب غسل الرأس بالخطمي: حدّثني محمّد بن الحسن، قال:<br/>حدّثني محمّد بن الحسن الصفّار، عن محمّد بن عيسى، عن أبي أيوب المدائني، عن ابن أبي عميرة، عن سفيان بن السمط، عن أبي عبد الله عليه السّلام، و الفضل الطبرسي في الآداب الدينية: 63، بقوله: و روي أن غسل الرأس، و وردت روايات كثيرة في مضمون هذا الحديث. انظر: كتاب زيد النرسي المطبوع ضمن الاصول الستة عشر: 37/190/205، الكافي 5/418:3، باب التزيّن يوم الجمعة، و ج 10/491:6، باب قصّ الأظفار، و 1/504 و 3، باب غسل الرأس، ثواب الأعمال: 1/19، باب ثواب غسل الرأس بالخطمي، كتاب العروس: 54، مكارم الأخلاق: 64، الدعوات: 201/80. </footnote>"
        },
        {
          "footnoteId": 714168858,
          "text": "<footnote id=\"903\"><mnote>(2)</mnote> رواه الصدوق مع زيادة في من لا يحضره الفقيه 294/125:1 - و عنه في مكارم الأخلاق: 4/61، الفصل الخامس في غسل الرأس بالخطمي و السدر - و زاد في آخره:<br/>«و كان ذلك سدرا من سدرة المنتهى»، و بلا زيادة في ثواب الأعمال: 2/20، باب ثواب غسل الرأس بورق السدر، فقال: أبي رحمه الله، قال: حدّثنا سعد بن عبد الله، عن محمّد بن عيسى، عن النوفلي، عن عيسى بن عبد الله العلوي، عن أبيه، عن جدّه، عن رسول الله صلّى الله عليه و آله، و عنه في أعلام الدين: 364، و الراوندي في الدعوات: 283/120 بقوله: و كان رسول الله صلّى الله عليه و آله قد اغتمّ‌، و روي في غسل الرأس بالسدر و خصوصا في يوم الجمعة روايات كثيرة. انظر: كتاب زيد النرسي المطبوع ضمن الاصول الستّة عشر:<br/>38/191/205 - و عنه في ثواب الأعمال: 1/20، باب ثواب غسل الرأس بورق <page number=\"144\"/>السدر، و عن ثواب الأعمال في أعلام الدين: 364 - الكافي 6/504:6، و 7/505، باب غسل الرأس، من لا يحضره الفقيه 295/125:1 و ح 296 - و عنه في مكارم الأخلاق: 61 - روضة الواعظين: 308، الآداب الدينية: 19/24، مكارم الأخلاق: 33. و لاحظ: السنن الكبرى للبيهقي 395:3. </footnote>"
        }
      ],
      "pageValue": "143",
      "isFreeStudy": true,
      "requestedContentType": "text",
      "providedContentType": "text",
      "isEmpty": false,
      "html": "<div class=\"CODE\">\n  <p id=\"p2756\" paragraph-id=\"2756\" class=\" G\">\n    <span class=\"GPA0 bookPage PageNo143\">143</span>[215] </p>\n  <p id=\"p2757\" paragraph-id=\"2757\" class=\" G\">\n    <span class=\"hadith\">\n      <span class=\"sanadHadith\">و روي عن <span class=\"Y\"><span class=\"maasoom\">أبي عبد الله عليه السّلام</span></span> أنّه قال: </span>«غسل الرأس بالخطمي ينفي الفقر و يزيد في الرزق»<span><sup><a class=\"NewFn\" href=\"#footnote902\" title=\"(1)  رواه الصدوق في من لا يحضره الفقيه 291/124:1، عن الصادق عليه السّلام - و عنه في مكارم الأخلاق: 2/60، الفصل الخامس في غسل الرأس بالخطمي و السدر - و في ثواب الأعمال: 2/19، باب ثواب غسل الرأس بالخطمي: حدّثني محمّد بن الحسن، قال:حدّثني محمّد بن الحسن الصفّار، عن محمّد بن عيسى، عن أبي أيوب المدائني، عن ابن أبي عميرة، عن سفيان بن السمط، عن أبي عبد الله عليه السّلام، و الفضل الطبرسي في الآداب الدينية: 63، بقوله: و روي أن غسل الرأس، و وردت روايات كثيرة في مضمون هذا الحديث. انظر: كتاب زيد النرسي المطبوع ضمن الاصول الستة عشر: 37/190/205، الكافي 5/418:3، باب التزيّن يوم الجمعة، و ج 10/491:6، باب قصّ الأظفار، و 1/504 و 3، باب غسل الرأس، ثواب الأعمال: 1/19، باب ثواب غسل الرأس بالخطمي، كتاب العروس: 54، مكارم الأخلاق: 64، الدعوات: 201/80. \">1</a></sup></span>.</span>\n  </p>\n  <p id=\"p2758\" paragraph-id=\"2758\" class=\" G\">[216] </p>\n  <p id=\"p2759\" paragraph-id=\"2759\" class=\" G\">\n    <span class=\"hadith\">\n      <span class=\"sanadHadith\">و قال: </span>\n      <span class=\"Y\">\n        <span class=\"maasoom\"></span>\n      </span>«إنّ <span class=\"Y\"><span class=\"maasoom\">رسول الله صلّى الله عليه و آله</span></span> اغتمّ ذات يوم فأمره جبريل عليه السّلام أن يغسل رأسه بالسدر»<span><sup><a class=\"NewFn\" href=\"#footnote903\" title=\"(2)  رواه الصدوق مع زيادة في من لا يحضره الفقيه 294/125:1 - و عنه في مكارم الأخلاق: 4/61، الفصل الخامس في غسل الرأس بالخطمي و السدر - و زاد في آخره:«و كان ذلك سدرا من سدرة المنتهى»، و بلا زيادة في ثواب الأعمال: 2/20، باب ثواب غسل الرأس بورق السدر، فقال: أبي رحمه الله، قال: حدّثنا سعد بن عبد الله، عن محمّد بن عيسى، عن النوفلي، عن عيسى بن عبد الله العلوي، عن أبيه، عن جدّه، عن رسول الله صلّى الله عليه و آله، و عنه في أعلام الدين: 364، و الراوندي في الدعوات: 283/120 بقوله: و كان رسول الله صلّى الله عليه و آله قد اغتمّ‌، و روي في غسل الرأس بالسدر و خصوصا في يوم الجمعة روايات كثيرة. انظر: كتاب زيد النرسي المطبوع ضمن الاصول الستّة عشر:38/191/205 - و عنه في ثواب الأعمال: 1/20، باب ثواب غسل الرأس بورق \">2</a></sup></span>.</span>\n  </p>\n  <p id=\"p2760\" paragraph-id=\"2760\" class=\" G\" />\n  <hr class=\"footnoteLine\" />\n  <span>\n    <div class=\"footnote OriginalDigit\" id=\"footnote902\" footnote-id=\"902\">(1) <page number=\"143\" /> رواه الصدوق في من لا يحضره الفقيه 291/124:1، عن الصادق عليه السّلام - و عنه في مكارم الأخلاق: 2/60، الفصل الخامس في غسل الرأس بالخطمي و السدر - و في ثواب الأعمال: 2/19، باب ثواب غسل الرأس بالخطمي: حدّثني محمّد بن الحسن، قال:<br />حدّثني محمّد بن الحسن الصفّار، عن محمّد بن عيسى، عن أبي أيوب المدائني، عن ابن أبي عميرة، عن سفيان بن السمط، عن أبي عبد الله عليه السّلام، و الفضل الطبرسي في الآداب الدينية: 63، بقوله: و روي أن غسل الرأس، و وردت روايات كثيرة في مضمون هذا الحديث. انظر: كتاب زيد النرسي المطبوع ضمن الاصول الستة عشر: 37/190/205، الكافي 5/418:3، باب التزيّن يوم الجمعة، و ج 10/491:6، باب قصّ الأظفار، و 1/504 و 3، باب غسل الرأس، ثواب الأعمال: 1/19، باب ثواب غسل الرأس بالخطمي، كتاب العروس: 54، مكارم الأخلاق: 64، الدعوات: 201/80. </div>\n    <div class=\"footnote OriginalDigit\" id=\"footnote903\" footnote-id=\"903\">(2)  رواه الصدوق مع زيادة في من لا يحضره الفقيه 294/125:1 - و عنه في مكارم الأخلاق: 4/61، الفصل الخامس في غسل الرأس بالخطمي و السدر - و زاد في آخره:<br />«و كان ذلك سدرا من سدرة المنتهى»، و بلا زيادة في ثواب الأعمال: 2/20، باب ثواب غسل الرأس بورق السدر، فقال: أبي رحمه الله، قال: حدّثنا سعد بن عبد الله، عن محمّد بن عيسى، عن النوفلي، عن عيسى بن عبد الله العلوي، عن أبيه، عن جدّه، عن رسول الله صلّى الله عليه و آله، و عنه في أعلام الدين: 364، و الراوندي في الدعوات: 283/120 بقوله: و كان رسول الله صلّى الله عليه و آله قد اغتمّ‌، و روي في غسل الرأس بالسدر و خصوصا في يوم الجمعة روايات كثيرة. انظر: كتاب زيد النرسي المطبوع ضمن الاصول الستّة عشر:<br />38/191/205 - و عنه في ثواب الأعمال: 1/20، باب ثواب غسل الرأس بورق </div>\n  </span>\n</div>",
      "bookPageVisitLogId": "2112FB50-798F-48E7-927D-ED45736BCB0F",
      "validation": {
        "code": 1,
        "type": "successful",
        "message": "محتوا در دسترس می باشد -  کتاب یا محدوده رایگان"
      }
    }
  ],
  "totalCount": 1,
  "statusCode": 200,
  "message": "OK",
  "exception": null,
  "validationMessages": null
}