{
  "isSuccess": true,
  "data": [
    {
      "pageNumber": 41,
      "sectionNumber": 1,
      "hasTextContent": true,
      "hasImageContent": true,
      "paragList": [
        {
          "paragraphId": 714169872,
          "paragNumber": 1,
          "tocNumber": 0,
          "text": "<p id=\"1127\"><page number=\"41\"/>[57] </p>"
        },
        {
          "paragraphId": 714169873,
          "paragNumber": 2,
          "tocNumber": 0,
          "text": "<p id=\"1128\"><format class=\"hadith\" who=\"14,4\" Id=\"57\" RevayatIndex=\"578\"><format class=\"sanadHadith\">و روى عن <format class=\"HQ\"><format class=\"maasoom\" maasoomNo=\"4\">أبيه عليه السّلام</format></format>، عن <format class=\"G\"><format class=\"maasoom\" maasoomNo=\"\">آبائه عليهم السّلام</format></format>، عن <format class=\"G\"><format class=\"maasoom\" maasoomNo=\"1\">علي بن أبي طالب عليه السّلام </format></format>قال<lfootnote noteId=\"154\">1</lfootnote>: «قال <format class=\"Y\"><format class=\"maasoom\" maasoomNo=\"14\">رسول الله صلّى الله عليه و آله</format></format>: </format>نزل عليّ جبريل بالحجامة و اليمين و الشاهد<lfootnote noteId=\"155\">2</lfootnote>، و يوم الأربعاء يوم نحس مستمرّ<lfootnote noteId=\"156\">3</lfootnote>»<lfootnote noteId=\"157\">4</lfootnote>.</format></p>"
        },
        {
          "paragraphId": 714169874,
          "paragNumber": 3,
          "tocNumber": 0,
          "text": "<p id=\"1129\">[58] </p>"
        },
        {
          "paragraphId": 714169875,
          "paragNumber": 4,
          "tocNumber": 0,
          "text": "<p id=\"1130\"><format class=\"hadith\" who=\"6\" Id=\"58\" RevayatIndex=\"579\"><format class=\"sanadHadith\">حدّثنا أبو سهل مرويه، قال: حدّثنا محمّد بن أحمد الدينوري، عن هارون بن مسلم، عن مسعدة بن صدقة، عن <format class=\"Y\"><format class=\"maasoom\" maasoomNo=\"6\">أبي عبد الله عليه السّلام</format></format>، قال: </format>«لم أدرك <page number=\"42\"/> أحدا من أهل بيتي ينهى من الحجامة يوم الأربعاء»<lfootnote noteId=\"158\">1</lfootnote>. </format></p>"
        }
      ],
      "taliqehList": null,
      "footnoteList": [
        {
          "footnoteId": 714170937,
          "text": "<footnote id=\"153\"><mnote>(3)</mnote> رواه الطبرسي في مكارم الأخلاق: 20/75، الفصل الرابع في الحجامة، عن زيد بن علي، <page number=\"41\"/>و القاضي بتفاوت يسير في دعائم الإسلام 512/145:2، عن رسول الله صلّى الله عليه و آله أنّه قال:<br/>«من احتجم يوم الأربعاء أو يوم السبت فأصابه وضح فلا يلم إلّا نفسه».<br/>نقلها العامّة في كثير من كتبهم، لاحظ: مسند ابن الجعد: 426، المصنّف لابن أبي شيبة الكوفي 459:5، علل الدارقطني 381:9 و 383، المعجم الكبير للطبراني 258:11، المصنّف للصنعاني 29:11. </footnote>"
        },
        {
          "footnoteId": 714170938,
          "text": "<footnote id=\"154\"><mnote>(1)</mnote> كلمة: «قال» أثبتناها من المصدر. </footnote>"
        },
        {
          "footnoteId": 714170939,
          "text": "<footnote id=\"155\"><mnote>(2)</mnote> في النسخة: «و اليمين على الشاهد» و قد صحّحناه ممّا روي عن رسول الله صلّى الله عليه و آله أنّه قضى بشهادة شاهد و يمين المدّعي، و قال صلّى الله عليه و آله: «إنّه نزل عليّ جبرئيل عليه السّلام بالحكم بشهادة شاهد و يمين صاحب الحق» و حكم به أمير المؤمنين عليه السّلام بالعراق. من لا يحضره الفقيه 3318/54:3، باب الحكم بشهادة الواحد و يمين المدعي، و الأمالي: 3/444 و 4/445، و انظر:<br/>الكافي 385:7، تهذيب الأحكام 272:6. </footnote>"
        },
        {
          "footnoteId": 714170940,
          "text": "<footnote id=\"156\"><mnote>(3)</mnote> قال القمي في كتاب المسلسلات: 111 بعد نقل رواية: و روي أنّ معنى مستمرّ أن يكون النهار نحسا من أوّله إلى الليل، و قال عليه السّلام: «إنّ معنى المستمرّ هو أن لا يذهب نحسه إلى أن يذهب من يوم الخميس ساعة». </footnote>"
        },
        {
          "footnoteId": 714170941,
          "text": "<footnote id=\"157\"><mnote>(4)</mnote> رواه الطبرسي في مكارم الأخلاق: 21/75، الفصل الرابع في الحجامة بعد الحديث المتقدّم، فقال: و روى الصادق عن آبائه عليهم السّلام عن رسول الله صلّى الله عليه و آله، و روى نحوه القاسم بن يحيى الراشدي في كتاب آداب أمير المؤمنين عليه السّلام: 388/249، و عنه في الخصال: 77/388 و 637.</footnote>"
        }
      ],
      "pageValue": "41",
      "isFreeStudy": true,
      "requestedContentType": "text",
      "providedContentType": "text",
      "isEmpty": false,
      "html": "<div class=\"CODE\">\n  <p id=\"p1127\" paragraph-id=\"1127\" class=\" G\">\n    <span class=\"GPA0 bookPage PageNo41\">41</span>[57] </p>\n  <p id=\"p1128\" paragraph-id=\"1128\" class=\" G\">\n    <span class=\"hadith\">\n      <span class=\"sanadHadith\">و روى عن <span class=\"HQ\"><span class=\"maasoom\">أبيه عليه السّلام</span></span>، عن <span class=\"G\"><span class=\"maasoom\">آبائه عليهم السّلام</span></span>، عن <span class=\"G\"><span class=\"maasoom\">علي بن أبي طالب عليه السّلام </span></span>قال<span><sup><a class=\"NewFn\" href=\"#footnote154\" title=\"(1)  كلمة: «قال» أثبتناها من المصدر. \">1</a></sup></span>: «قال <span class=\"Y\"><span class=\"maasoom\">رسول الله صلّى الله عليه و آله</span></span>: </span>نزل عليّ جبريل بالحجامة و اليمين و الشاهد<span><sup><a class=\"NewFn\" href=\"#footnote155\" title=\"(2)  في النسخة: «و اليمين على الشاهد» و قد صحّحناه ممّا روي عن رسول الله صلّى الله عليه و آله أنّه قضى بشهادة شاهد و يمين المدّعي، و قال صلّى الله عليه و آله: «إنّه نزل عليّ جبرئيل عليه السّلام بالحكم بشهادة شاهد و يمين صاحب الحق» و حكم به أمير المؤمنين عليه السّلام بالعراق. من لا يحضره الفقيه 3318/54:3، باب الحكم بشهادة الواحد و يمين المدعي، و الأمالي: 3/444 و 4/445، و انظر:الكافي 385:7، تهذيب الأحكام 272:6. \">2</a></sup></span>، و يوم الأربعاء يوم نحس مستمرّ<span><sup><a class=\"NewFn\" href=\"#footnote156\" title=\"(3)  قال القمي في كتاب المسلسلات: 111 بعد نقل رواية: و روي أنّ معنى مستمرّ أن يكون النهار نحسا من أوّله إلى الليل، و قال عليه السّلام: «إنّ معنى المستمرّ هو أن لا يذهب نحسه إلى أن يذهب من يوم الخميس ساعة». \">3</a></sup></span>»<span><sup><a class=\"NewFn\" href=\"#footnote157\" title=\"(4)  رواه الطبرسي في مكارم الأخلاق: 21/75، الفصل الرابع في الحجامة بعد الحديث المتقدّم، فقال: و روى الصادق عن آبائه عليهم السّلام عن رسول الله صلّى الله عليه و آله، و روى نحوه القاسم بن يحيى الراشدي في كتاب آداب أمير المؤمنين عليه السّلام: 388/249، و عنه في الخصال: 77/388 و 637.\">4</a></sup></span>.</span>\n  </p>\n  <p id=\"p1129\" paragraph-id=\"1129\" class=\" G\">[58] </p>\n  <p id=\"p1130\" paragraph-id=\"1130\" class=\" G\">\n    <span class=\"hadith\">\n      <span class=\"sanadHadith\">حدّثنا أبو سهل مرويه، قال: حدّثنا محمّد بن أحمد الدينوري، عن هارون بن مسلم، عن مسعدة بن صدقة، عن <span class=\"Y\"><span class=\"maasoom\">أبي عبد الله عليه السّلام</span></span>، قال: </span>«لم أدرك </span>\n  </p>\n  <hr class=\"footnoteLine\" />\n  <span>\n    <div class=\"footnote OriginalDigit\" id=\"footnote153\" footnote-id=\"153\"><page number=\"41\" />و القاضي بتفاوت يسير في دعائم الإسلام 512/145:2، عن رسول الله صلّى الله عليه و آله أنّه قال:<br />«من احتجم يوم الأربعاء أو يوم السبت فأصابه وضح فلا يلم إلّا نفسه».<br />نقلها العامّة في كثير من كتبهم، لاحظ: مسند ابن الجعد: 426، المصنّف لابن أبي شيبة الكوفي 459:5، علل الدارقطني 381:9 و 383، المعجم الكبير للطبراني 258:11، المصنّف للصنعاني 29:11. </div>\n    <div class=\"footnote OriginalDigit\" id=\"footnote154\" footnote-id=\"154\">(1)  كلمة: «قال» أثبتناها من المصدر. </div>\n    <div class=\"footnote OriginalDigit\" id=\"footnote155\" footnote-id=\"155\">(2)  في النسخة: «و اليمين على الشاهد» و قد صحّحناه ممّا روي عن رسول الله صلّى الله عليه و آله أنّه قضى بشهادة شاهد و يمين المدّعي، و قال صلّى الله عليه و آله: «إنّه نزل عليّ جبرئيل عليه السّلام بالحكم بشهادة شاهد و يمين صاحب الحق» و حكم به أمير المؤمنين عليه السّلام بالعراق. من لا يحضره الفقيه 3318/54:3، باب الحكم بشهادة الواحد و يمين المدعي، و الأمالي: 3/444 و 4/445، و انظر:<br />الكافي 385:7، تهذيب الأحكام 272:6. </div>\n    <div class=\"footnote OriginalDigit\" id=\"footnote156\" footnote-id=\"156\">(3)  قال القمي في كتاب المسلسلات: 111 بعد نقل رواية: و روي أنّ معنى مستمرّ أن يكون النهار نحسا من أوّله إلى الليل، و قال عليه السّلام: «إنّ معنى المستمرّ هو أن لا يذهب نحسه إلى أن يذهب من يوم الخميس ساعة». </div>\n    <div class=\"footnote OriginalDigit\" id=\"footnote157\" footnote-id=\"157\">(4)  رواه الطبرسي في مكارم الأخلاق: 21/75، الفصل الرابع في الحجامة بعد الحديث المتقدّم، فقال: و روى الصادق عن آبائه عليهم السّلام عن رسول الله صلّى الله عليه و آله، و روى نحوه القاسم بن يحيى الراشدي في كتاب آداب أمير المؤمنين عليه السّلام: 388/249، و عنه في الخصال: 77/388 و 637.</div>\n  </span>\n</div>",
      "bookPageVisitLogId": "0418E3BB-689A-4DAE-8ED2-5386935BCBDF",
      "validation": {
        "code": 1,
        "type": "successful",
        "message": "محتوا در دسترس می باشد -  کتاب یا محدوده رایگان"
      }
    }
  ],
  "totalCount": 1,
  "statusCode": 200,
  "message": "OK",
  "exception": null,
  "validationMessages": null
}